MANIFEST.in
README.rst
setup.py
docs/HISTORY.txt
docs/INSTALL.txt
docs/LICENSE.GPL
docs/LICENSE.txt
ftw/__init__.py
ftw.task.egg-info/PKG-INFO
ftw.task.egg-info/SOURCES.txt
ftw.task.egg-info/dependency_links.txt
ftw.task.egg-info/entry_points.txt
ftw.task.egg-info/namespace_packages.txt
ftw.task.egg-info/not-zip-safe
ftw.task.egg-info/requires.txt
ftw.task.egg-info/top_level.txt
ftw/task/__init__.py
ftw/task/config.py
ftw/task/configure.zcml
ftw/task/interfaces.py
ftw/task/lawgiver.zcml
ftw/task/setuphandlers.py
ftw/task/testing.py
ftw/task/vocabularies.py
ftw/task/browser/__init__.py
ftw/task/browser/configure.zcml
ftw/task/browser/task.pt
ftw/task/browser/task.py
ftw/task/browser/tasktab.py
ftw/task/content/__init__.py
ftw/task/content/configure.zcml
ftw/task/content/task.py
ftw/task/latex/__init__.py
ftw/task/latex/configure.zcml
ftw/task/latex/workspace.py
ftw/task/latex/templates/tasks_listing.pt
ftw/task/locales/ftw.task-manual.pot
ftw/task/locales/ftw.task.pot
ftw/task/locales/plone.pot
ftw/task/locales/de/LC_MESSAGES/ftw.task.po
ftw/task/locales/de/LC_MESSAGES/plone.po
ftw/task/locales/fr/LC_MESSAGES/ftw.task.po
ftw/task/locales/fr/LC_MESSAGES/plone.po
ftw/task/portlets/__init__.py
ftw/task/portlets/configure.zcml
ftw/task/portlets/mytasks.pt
ftw/task/portlets/mytasks.py
ftw/task/profiles/default/catalog.xml
ftw/task/profiles/default/factorytool.xml
ftw/task/profiles/default/ftw.task.setuphandlers.txt
ftw/task/profiles/default/metadata.xml
ftw/task/profiles/default/portlets.xml
ftw/task/profiles/default/propertiestool.xml
ftw/task/profiles/default/rolemap.xml
ftw/task/profiles/default/types.xml
ftw/task/profiles/default/types/Task.xml
ftw/task/tests/__init__.py
ftw/task/tests/builders.py
ftw/task/tests/task.txt
ftw/task/tests/test.zcml
ftw/task/tests/test_functional_doctest.py
ftw/task/tests/test_task_tab.py
ftw/task/tests/test_task_view.py
ftw/task/tests/test_vocabularies.py
ftw/task/upgrades/__init__.py
ftw/task/upgrades/configure.zcml
ftw/task/upgrades/to2001.py