Metadata-Version: 1.1
Name: ftw.task
Version: 3.0.1
Summary: A simple task content type for Plone.
Home-page: https://github.com/4teamwork/ftw.task
Author: Mathias Leimgruber
Author-email: mailto:info@4teamwork.ch
License: GPL2
Keywords: ftw task plone
Platform: UNKNOWN
Classifier: Framework :: Plone
Classifier: Framework :: Plone :: 4.3
Classifier: License :: OSI Approved :: GNU General Public License (GPL)
Classifier: Programming Language :: Python
Classifier: Programming Language :: Python :: 2.6
Classifier: Topic :: Software Development :: Libraries :: Python Modules
